maglev.py
mindpowered_maglev-0.7.21.dist-info/LICENSE.txt
mindpowered_maglev-0.7.21.dist-info/METADATA
mindpowered_maglev-0.7.21.dist-info/WHEEL
mindpowered_maglev-0.7.21.dist-info/top_level.txt
mindpowered_maglev-0.7.21.dist-info/RECORD
